.gitignore
.travis.yml
CHANGES.rst
CONTRIBUTORS.txt
COPYRIGHT.txt
LICENSE.txt
MANIFEST.in
README.rst
TODO.txt
setup.cfg
setup.py
tox.ini
docs/Makefile
docs/api.rst
docs/conf.py
docs/index.rst
docs/_static/logo_hi.png
docs/_static/repoze.css
repoze/__init__.py
repoze.vhm3.egg-info/PKG-INFO
repoze.vhm3.egg-info/SOURCES.txt
repoze.vhm3.egg-info/dependency_links.txt
repoze.vhm3.egg-info/entry_points.txt
repoze.vhm3.egg-info/namespace_packages.txt
repoze.vhm3.egg-info/not-zip-safe
repoze.vhm3.egg-info/requires.txt
repoze.vhm3.egg-info/top_level.txt
repoze/vhm/__init__.py
repoze/vhm/constants.py
repoze/vhm/middleware.py
repoze/vhm/utils.py
repoze/vhm/tests/__init__.py
repoze/vhm/tests/test_middleware.py
repoze/vhm/tests/test_utils.py